s3_sqlite3/__init__.py
s3_sqlite3/s3_sqlite3.py
s3_sqlite3/s3vfs.py
s3_sqlite3/s3vfsfile.py
S3Sqlite3-0.2.dist-info/LICENSE.md
S3Sqlite3-0.2.dist-info/METADATA
S3Sqlite3-0.2.dist-info/WHEEL
S3Sqlite3-0.2.dist-info/top_level.txt
S3Sqlite3-0.2.dist-info/RECORD
